aletheiacosmo/AletheiaEmu.py
aletheiacosmo/__init__.py
aletheiacosmo/cosmology.py
aletheiacosmo/growth.py
aletheiacosmo/data/planck_2018_lcdm_parcov.dat
aletheiacosmo-0.1.1.dist-info/licenses/LICENSE
aletheiacosmo-0.1.1.dist-info/METADATA
aletheiacosmo-0.1.1.dist-info/WHEEL
aletheiacosmo-0.1.1.dist-info/top_level.txt
aletheiacosmo-0.1.1.dist-info/RECORD
