Metadata-Version: 2.4
Name: AletheiaCosmo
Version: 0.1.1
Summary: An emulator of the non-linear matter power spectrum based on the evolution mapping approach.
Author-email: "Ariel G. Sanchez" <arielsan@mpe.mpg.de>
License: MIT License
Project-URL: Homepage, https://gitlab.mpcdf.mpg.de/arielsan/aletheia
Project-URL: Bug Tracker, https://gitlab.mpcdf.mpg.de/arielsan/aletheia/-/issues
Classifier: Programming Language :: Python :: 3
Classifier: License :: OSI Approved :: MIT License
Classifier: Operating System :: OS Independent
Classifier: Topic :: Scientific/Engineering :: Astronomy
Classifier: Intended Audience :: Science/Research
Requires-Python: >=3.9
License-File: LICENSE
Requires-Dist: numpy
Requires-Dist: scipy
Requires-Dist: camb
Requires-Dist: scikit-learn~=1.7.2
Requires-Dist: appdirs
Requires-Dist: skops
Dynamic: license-file
